llama_index/tools/requests/__init__.py
llama_index/tools/requests/base.py
llama_index_tools_requests-0.5.1.dist-info/METADATA
llama_index_tools_requests-0.5.1.dist-info/WHEEL
llama_index_tools_requests-0.5.1.dist-info/licenses/LICENSE
llama_index_tools_requests-0.5.1.dist-info/RECORD
